[
    {
        "title": "Squirrel Throne",
        "imageUrl": "/Wildlife/wildlife-landscape-1.jpg",
        "orientation": "Landscape",
        "location": {
            "geoLocationtitle": "Jacques Cartier",
            "lat": "",
            "lon": ""
        },
        "author": "Kenneth Martens",
        "tags": [
            "Wildife",
            "Squirrel",
            "Canada"
        ]
    },
    {
        "title": "Close-up of a Bison",
        "imageUrl": "/Wildlife/wildlife-portrait-4.jpg",
        "orientation": "Portrait",
        "location": {
            "geoLocationtitle": "Badlands NP",
            "lat": "",
            "lon": ""
        },
        "author": "Corrina Martens",
        "tags": [
            "Wildife"
        ]
    },
    {
        "title": "The Showdown",
        "imageUrl": "/Wildlife/wildlife-portrait-1.jpg",
        "orientation": "Portrait",
        "location": {
            "geoLocationtitle": "Somewhere in Illinois",
            "lat": "",
            "lon": ""
        },
        "author": "Kenneth Martens",
        "tags": [
            "Wildife",
            "Prairie Chicken",
            "Avian",
            "Illinois"
        ]
    }
]